CHANGES.rst
MANIFEST.in
README.rst
bootstrap-buildout.py
buildout.cfg
setup.py
shell.py
mr.developer.shell.egg-info/PKG-INFO
mr.developer.shell.egg-info/SOURCES.txt
mr.developer.shell.egg-info/dependency_links.txt
mr.developer.shell.egg-info/entry_points.txt
mr.developer.shell.egg-info/not-zip-safe
mr.developer.shell.egg-info/requires.txt
mr.developer.shell.egg-info/top_level.txt