Metadata-Version: 1.1
Name: mr.developer.shell
Version: 0.0.1
Summary: mr.developer extension to run shell commands on repositories.
Home-page: http://github.com/gforcada/mr.developer.shell
Author: Gil Forcada Codinachs
Author-email: gilforcada@gmail.com
License: BSD
Keywords: mr.developer extension shell
Platform: UNKNOWN
Classifier: Development Status :: 3 - Alpha
Classifier: Programming Language :: Python
Classifier: Programming Language :: Python :: 3
Classifier: Framework :: Buildout
Classifier: Topic :: Software Development
Classifier: Topic :: Software Development :: Libraries :: Python Modules
